sound_field_analysis/__init__.py
sound_field_analysis/_version.py
sound_field_analysis/gen.py
sound_field_analysis/io.py
sound_field_analysis/lebedev.py
sound_field_analysis/plot.py
sound_field_analysis/process.py
sound_field_analysis/sph.py
sound_field_analysis/utils.py
sound_field_analysis-2021.2.4.dist-info/LICENSE
sound_field_analysis-2021.2.4.dist-info/METADATA
sound_field_analysis-2021.2.4.dist-info/WHEEL
sound_field_analysis-2021.2.4.dist-info/top_level.txt
sound_field_analysis-2021.2.4.dist-info/RECORD
