Metadata-Version: 2.1
Name: sound-field-analysis
Version: 2021.2.4
Summary: Analyze, visualize and process sound field data recorded by spherical microphone arrays.
Home-page: https://github.com/AppliedAcousticsChalmers/sound_field_analysis-py/
Author: Chalmers University of Technology / Jens Ahrens
Author-email: jens.ahrens@chalmers.se
License: GPLv3
Keywords: sound field analysis spherical microphone array
Platform: UNKNOWN
Classifier: Development Status :: 4 - Beta
Classifier: Intended Audience :: Science/Research
Classifier: Topic :: Multimedia :: Sound/Audio
Classifier: License :: OSI Approved :: MIT License
Classifier: Programming Language :: Python :: 3.7
Classifier: Operating System :: OS Independent
Requires-Python: >=3.7
Requires-Dist: scipy
Requires-Dist: numpy
Requires-Dist: pysofaconventions
Provides-Extra: examples
Requires-Dist: jupyter ; extra == 'examples'
Provides-Extra: plotting
Requires-Dist: plotly ; extra == 'plotting'
Provides-Extra: testing
Requires-Dist: pytest ; extra == 'testing'
